class_registry/__init__.py
class_registry/auto_import.py
class_registry/models.py
class_registry/sites.py
class_registry/tests/__init__.py
class_registry/tests/test_registry.py
class_registry/tests/demo/__init__.py
class_registry/tests/demo/actions/__init__.py
class_registry/tests/demo/actions/one.py
class_registry/tests/demo/actions/three.py
class_registry/tests/demo/actions/two.py
django_class_registry-1.1.2.dist-info/LICENSE
django_class_registry-1.1.2.dist-info/METADATA
django_class_registry-1.1.2.dist-info/WHEEL
django_class_registry-1.1.2.dist-info/top_level.txt
django_class_registry-1.1.2.dist-info/RECORD
